{
  "nombre": "weber block",
  "url": "https://www.ar.weber/revocar-paredes/mezclas-de-asiento/weber-block",
  "descripcion": "Inicio Revocar paredes Mezclas de asiento",
  "datos_tecnicos": "Inicio\nRevocar paredes\nMezclas de asiento\nweber block\nShow gallery\nweber block\nMezcla de asiento hidrófuga, apta para bloques de hormigón, ladrillos cerámicos y ladrillos comunes.\nAditivado con Ceresita\nControl de asentamiento\nFácil aplicacion\nManual\nSoporte\nFachada,\nPared Exterior,\nPared Interna\nCalculadora de consumo\nAcerca de este producto\n• Verificar la horizontalidad de la base y fijar guías verticales como referencia para lograr una pared a plomo.\n• Humedecer la superficie\nCaracterísticas y beneficios\nExcelente control de asentamiento.\nFácil aplicación.\nDocumentación del producto\nFicha de producto\nFP_weber_block.pdf\n(PDF - 960,66 KB)\nDescargar\nEnviar\nHoja Técnica\nFT weber block.pdf\n(PDF - 284,23 KB)\nDescargar\nEnviar\nHoja de Seguridad\nHS weber block\n(PDF - 100 KB)\nDescargar\nEnviar\nTutoriales y videos\nComenzar tutorial\nVer video\nProductos relacionados con weber block\nweber print XC\nEndurecedor superficial para pisos de hormigón con cuarzo",
  "documentos": [
    {
      "nombre": "FP_weber_block.pdf",
      "url": "https://www.ar.weber/files/ar/2018-09/FP_weber_block.pdf"
    },
    {
      "nombre": "FT weber block.pdf",
      "url": "https://www.ar.weber/files/ar/2018-05/FT_weber_block.pdf"
    },
    {
      "nombre": "HS weber block",
      "url": "https://www.ar.weber/files/ar/2018-09/HS_weber_block.pdf"
    }
  ],
  "scrapeado_en": "2026-06-02T02:00:50.462837"
}